{
  "bootstrap_profile": "B0 (human approval required)",
  "developer_health_checks": "the legacy `sentinel` command runs six public developer health checks; it is not the Stage-0 gate or hidden escrow",
  "live_germline_mutation_enabled": false,
  "maturity": "PreStage0",
  "maturity_transitions": [
    "PreStage0",
    "Stage0GatePassed",
    "Stage1B0",
    "Stage2B0"
  ],
  "missing_evidence": [
    {
      "id": "bazel",
      "requirement": "canonical Bazel workspace, crate target parity, and clean-checkout Stage-0 suite"
    },
    {
      "id": "mission",
      "requirement": "frozen public mission battery and category floors"
    },
    {
      "id": "escrow",
      "requirement": "operator-mounted root-of-trust and hidden-sentinel escrow validation"
    },
    {
      "id": "promotion",
      "requirement": "B0-approved atomic Git admission, durable journal, descendant inheritance, and rollback"
    },
    {
      "id": "constitution",
      "requirement": "digest-checked constitutional semantics with non-vacuous executable invariants"
    },
    {
      "id": "membrane",
      "requirement": "end-to-end capability and ingress boundary enforcement"
    },
    {
      "id": "external_value",
      "requirement": "independently verified sealed external-value campaign"
    }
  ]
}
